README.md
setup.cfg
setup.py
pyjekyll/JekyllPost.py
pyjekyll/JekyllPostContainer.py
pyjekyll/JekyllSite.py
pyjekyll/__init__.py
pyjekyll.egg-info/PKG-INFO
pyjekyll.egg-info/SOURCES.txt
pyjekyll.egg-info/dependency_links.txt
pyjekyll.egg-info/top_level.txt