Metadata-Version: 2.4
Name: pyjekyll
Version: 0.4
Summary: A Jekyll Python library for handling Jekyll static sites
Home-page: https://github.com/fantastic001/pyjekyll
Download-URL: https://github.com/fantastic001/pyjekyll/tarball/0.3
Author: Stefan Nožinić
Author-email: stefan@lugons.org
Keywords: jekyll
Classifier: Development Status :: 4 - Beta
Classifier: Intended Audience :: Developers
Classifier: License :: OSI Approved :: MIT License
Classifier: Programming Language :: Python :: 3
Classifier: Programming Language :: Python :: 3.7
Classifier: Programming Language :: Python :: 3.8
Classifier: Programming Language :: Python :: 3.9
Classifier: Programming Language :: Python :: 3.10
Classifier: Topic :: Software Development :: Libraries :: Python Modules
Requires-Python: >=3.7
Dynamic: author
Dynamic: author-email
Dynamic: classifier
Dynamic: download-url
Dynamic: home-page
Dynamic: keywords
Dynamic: requires-python
Dynamic: summary
